pySpacebroClient/__init__.py
pySpacebroClient/pySpacebroClient.py
pySpacebroClient-0.0.3.dist-info/DESCRIPTION.rst
pySpacebroClient-0.0.3.dist-info/METADATA
pySpacebroClient-0.0.3.dist-info/RECORD
pySpacebroClient-0.0.3.dist-info/WHEEL
pySpacebroClient-0.0.3.dist-info/metadata.json
pySpacebroClient-0.0.3.dist-info/top_level.txt
