Metadata-Version: 2.0
Name: pySpacebroClient
Version: 0.0.3
Summary: Connect easily to a spacebro server
Home-page: https://github.com/spacebro/pySpacebroClient
Author: Soixante circuits
Author-email: emmanuel@soixantecircuits.fr
License: MIT
Keywords: spacebro socket.io socketio client
Platform: UNKNOWN
Classifier: Development Status :: 3 - Alpha
Classifier: Intended Audience :: Developers
Classifier: Topic :: Utilities
Classifier: Topic :: System :: Networking
Classifier: License :: OSI Approved :: MIT License
Classifier: Programming Language :: Python :: 2
Classifier: Programming Language :: Python :: 2.7
Requires-Python: >=2.6, <3
Requires-Dist: socketIO-client-nexus (>=0.7.5)
Provides-Extra: dev
Provides-Extra: test
Requires-Dist: dotmap (>=1.2.17); extra == 'test'
Requires-Dist: mock (>=1.0.1); extra == 'test'
